ranploy/__init__.py
ranploy/main.py
ranploy-0.0.2.dist-info/METADATA
ranploy-0.0.2.dist-info/WHEEL
ranploy-0.0.2.dist-info/entry_points.txt
ranploy-0.0.2.dist-info/top_level.txt
ranploy-0.0.2.dist-info/RECORD
