Metadata-Version: 2.1
Name: ranploy
Version: 0.0.2
Summary: UNKNOWN
Home-page: https://github.com/cleanunicorn/ranploy
Author: Daniel Luca
Author-email: daniel.luca@consensys.net
License: MIT
Platform: UNKNOWN
